flask_bootstrap_components/__init__.py
flask_bootstrap_components/base.py
flask_bootstrap_components/breadcrumbs.py
flask_bootstrap_components/buttons.py
flask_bootstrap_components/component.py
flask_bootstrap_components/csrf.py
flask_bootstrap_components/forms.py
flask_bootstrap_components/grid.py
flask_bootstrap_components/markup.py
flask_bootstrap_components/nav.py
flask_bootstrap_components/tables.py
flask_bootstrap_components/toolbars.py
flask_bootstrap_components/utils.py
flask_bootstrap_components/templates/flask_bootstrap_components/internal/paged_table.html
flask_bootstrap_components/templates/flask_bootstrap_components/internal/table.html
Flask_Bootstrap_Components-0.2.1.dist-info/LICENSE
Flask_Bootstrap_Components-0.2.1.dist-info/METADATA
Flask_Bootstrap_Components-0.2.1.dist-info/WHEEL
Flask_Bootstrap_Components-0.2.1.dist-info/top_level.txt
Flask_Bootstrap_Components-0.2.1.dist-info/RECORD
