Metadata-Version: 2.1
Name: Flask-Bootstrap-Components
Version: 0.2.1
Summary: Collection of HTML generation helpers for Flask with Bootstrap 4
Home-page: https://github.com/adh/flask-bootstrap-components
Author: Ales Hakl
Author-email: ales@hakl.net
License: MIT
Keywords: flask bootstrap
Classifier: Development Status :: 3 - Alpha
Classifier: Framework :: Flask
Classifier: License :: OSI Approved :: MIT License
Classifier: Intended Audience :: Developers
Classifier: Programming Language :: Python :: 3
Classifier: Programming Language :: Python :: 3.3
Classifier: Programming Language :: Python :: 3.4
Classifier: Programming Language :: Python :: 3.5
License-File: LICENSE
Requires-Dist: Flask >=1.0
